thresholdmodeling/__init__.py
thresholdmodeling/thresh_modeling.py
thresholdmodeling-0.0.1.dist-info/LICENSE
thresholdmodeling-0.0.1.dist-info/METADATA
thresholdmodeling-0.0.1.dist-info/WHEEL
thresholdmodeling-0.0.1.dist-info/top_level.txt
thresholdmodeling-0.0.1.dist-info/RECORD
